virtualenv.py
virtualenv_support/__init__.py
virtualenv_support/pip-19.1.1-py2.py3-none-any.whl
virtualenv_support/pip-19.3.1-py2.py3-none-any.whl
virtualenv_support/setuptools-42.0.2-py2.py3-none-any.whl
virtualenv_support/wheel-0.33.6-py2.py3-none-any.whl
virtualenv_trobz-16.7.10.1.dist-info/LICENSE.txt
virtualenv_trobz-16.7.10.1.dist-info/METADATA
virtualenv_trobz-16.7.10.1.dist-info/WHEEL
virtualenv_trobz-16.7.10.1.dist-info/entry_points.txt
virtualenv_trobz-16.7.10.1.dist-info/top_level.txt
virtualenv_trobz-16.7.10.1.dist-info/zip-safe
virtualenv_trobz-16.7.10.1.dist-info/RECORD
