Metadata-Version: 2.1
Name: virtualenv-trobz
Version: 16.7.10.1
Summary: Virtual Python Environment builder, trobz\'s fork
Home-page: https://virtualenv.pypa.io/
Author: Ian Bicking
Author-email: ianb@colorstudy.com
Maintainer: Bernat Gabor
Maintainer-email: gaborjbernat@gmail.com
License: MIT
Project-URL: Source, https://github.com/trobz/virtualenv/tree/trobz
Project-URL: Tracker, https://github.com/trobz/virtualenv/issues
Keywords: virtual,environments,isolated
Platform: any
Classifier: Development Status :: 5 - Production/Stable
Classifier: Intended Audience :: Developers
Classifier: License :: OSI Approved :: MIT License
Classifier: Operating System :: POSIX
Classifier: Operating System :: Microsoft :: Windows
Classifier: Operating System :: MacOS :: MacOS X
Classifier: Topic :: Software Development :: Testing
Classifier: Topic :: Software Development :: Libraries
Classifier: Topic :: Utilities
Classifier: Programming Language :: Python :: 2
Classifier: Programming Language :: Python :: 2.7
Classifier: Programming Language :: Python :: 3
Classifier: Programming Language :: Python :: 3.4
Classifier: Programming Language :: Python :: 3.5
Classifier: Programming Language :: Python :: 3.6
Classifier: Programming Language :: Python :: 3.7
Requires-Python: !=3.0.*,!=3.1.*,!=3.2.*,!=3.3.*,>=2.7
Provides-Extra: docs
Requires-Dist: sphinx (<2,>=1.8.0) ; extra == 'docs'
Requires-Dist: towncrier (>=18.5.0) ; extra == 'docs'
Requires-Dist: sphinx-rtd-theme (<1,>=0.4.2) ; extra == 'docs'
Provides-Extra: testing
Requires-Dist: pytest (<5,>=4.0.0) ; extra == 'testing'
Requires-Dist: coverage (<5,>=4.5.0) ; extra == 'testing'
Requires-Dist: pytest-timeout (<2,>=1.3.0) ; extra == 'testing'
Requires-Dist: six (<2,>=1.10.0) ; extra == 'testing'
Requires-Dist: pytest-xdist ; extra == 'testing'
Requires-Dist: pytest-localserver ; extra == 'testing'
Requires-Dist: pypiserver ; extra == 'testing'
Requires-Dist: mock ; (python_version < "3.3") and extra == 'testing'
Requires-Dist: xonsh ; (python_version >= "3.5") and extra == 'testing'
